paramap/__init__.py
paramap/base.py
paramap/fields.py
paramap/registry.py
paramap/types.py
paramap-0.1.5.dist-info/LICENSE
paramap-0.1.5.dist-info/METADATA
paramap-0.1.5.dist-info/WHEEL
paramap-0.1.5.dist-info/top_level.txt
paramap-0.1.5.dist-info/RECORD
