Metadata-Version: 2.1
Name: paramap
Version: 0.1.5
Summary: Easily map flat dictionaries to object representations
Home-page: https://github.com/GrayTable/paramap
Author: Kamil Biel
Author-email: hello@kamilbiel.com
License: MIT
Platform: UNKNOWN
Classifier: Programming Language :: Python :: 3
Classifier: License :: OSI Approved :: MIT License
Classifier: Operating System :: OS Independent
Requires-Python: >=3.6
